django_fitbit_healthkit/__init__.py
django_fitbit_healthkit/admin.py
django_fitbit_healthkit/apps.py
django_fitbit_healthkit/methods.py
django_fitbit_healthkit/models.py
django_fitbit_healthkit/urls.py
django_fitbit_healthkit/util.py
django_fitbit_healthkit/views.py
django_fitbit_healthkit/migrations/0001_initial.py
django_fitbit_healthkit/migrations/__init__.py
django_fitbit_healthkit/templates/fitbit/success.html
sample/__init__.py
sample/asgi.py
sample/settings.py
sample/urls.py
sample/views.py
sample/wsgi.py
tests/__init__.py
tests/test_methods.py
tests/test_models.py
tests/test_util.py
tests/test_views.py
django_fitbit_healthkit-0.6.dist-info/LICENSE
django_fitbit_healthkit-0.6.dist-info/METADATA
django_fitbit_healthkit-0.6.dist-info/WHEEL
django_fitbit_healthkit-0.6.dist-info/top_level.txt
django_fitbit_healthkit-0.6.dist-info/RECORD
