Metadata-Version: 2.1
Name: django-fitbit-healthkit
Version: 0.6
Summary: A Django app to access Fitbit Web APIs.
Home-page: https://django-fitbit-healthkit.andyreagan.github.io
Author: Andy Reagan
Author-email: andy@andyreagan.com
License: BSD-3-Clause
Classifier: Environment :: Web Environment
Classifier: Framework :: Django
Classifier: Framework :: Django :: 5.0
Classifier: Intended Audience :: Developers
Classifier: License :: OSI Approved :: BSD License
Classifier: Operating System :: OS Independent
Classifier: Programming Language :: Python
Classifier: Programming Language :: Python :: 3
Classifier: Programming Language :: Python :: 3 :: Only
Classifier: Programming Language :: Python :: 3.10
Classifier: Programming Language :: Python :: 3.11
Classifier: Programming Language :: Python :: 3.12
Classifier: Topic :: Internet :: WWW/HTTP
Classifier: Topic :: Internet :: WWW/HTTP :: Dynamic Content
Requires-Python: >=3.10
License-File: LICENSE
Requires-Dist: Django >=4.0
Requires-Dist: requests >=2.31.0
